{
  "uuid": "62933cb0-ece5-426c-b517-e997d90e56f9",
  "shortName": "Kart",
  "longName": "Kart",
  "companyName": "Matt Williams",
  "versionLabel": "1.0",
  "sdkVersion": "3",
  "targetPlatforms": ["aplite", "basalt"],
  "watchapp": {
    "watchface": false
  },
  "appKeys": {
    "dummy": 0
  },
  "resources": {
    "media": [
      {
        "menuIcon": true,
        "name": "IMAGE_MENU_ICON",
        "file": "icon.png",
        "type": "png"
      },
      {
        "name": "KART_BLACK",
        "file": "kart_black.png",
        "type": "png"
      },
      {
        "name": "KART_WHITE",
        "file": "kart_white.png",
        "type": "png"
      },
      {
        "name": "KART_BLACK2",
        "file": "kart_black2.png",
        "type": "png"
      },
      {
        "name": "KART_WHITE2",
        "file": "kart_white2.png",
        "type": "png"
      },
      {
        "name": "KART_BLACK3",
        "file": "kart_black3.png",
        "type": "png"
      },
      {
        "name": "KART_WHITE3",
        "file": "kart_white3.png",
        "type": "png"
      },
      {
        "name": "TILES",
        "file": "tiles.png",
        "type": "png"
      },
      {
        "name": "SKY",
        "file": "sky.png",
        "type": "png"
      },
      {
        "name": "FONT",
        "file": "font.png",
        "type": "png"
      },
      {
        "name": "TRACK1",
        "file": "track1.dat",
        "type": "raw"
      },
      {
        "name": "TRACK1_THUMBNAIL",
        "file": "track1_thumbnail.png",
        "type": "png"
      },
      {
        "name": "TRACK2",
        "file": "track2.dat",
        "type": "raw"
      },
      {
        "name": "TRACK2_THUMBNAIL",
        "file": "track2_thumbnail.png",
        "type": "png"
      }
    ]
  }
}
